16bitSingleCycleMIPS/16bitMIPS.v
`timescale 1ns/100ps


module CPU(ROUT, clk,reset);
	output [15:0] ROUT;
	input clk, reset;

	wire [15:0] AluOut, PCout, WDATA, RDATA;
	wire [31:0] Inst;
	MIPS M(AluOut, PCout, ROUT, DataWrite, WDATA, RDATA, Inst, clk, reset);
	InnstructionMem I(Inst, PCout);
	DataMem D(RDATA, AluOut, WDATA,  DataWrite, clk);

endmodule

module MIPS(AluOut, PCout, ROUT, DataWrite, WDATA, RDATA, Inst, clk, reset);
	output [15:0] AluOut, PCout, ROUT;
	output [15:0] WDATA;
	output DataWrite;
	input clk, reset;
	input [15:0] RDATA;
	input [31:0] Inst;

	wire [2:0] AluCont;

	Controller C0(DataToReg, DataWrite, Branch, AluMux, 
					RegAddress, RegWrite, AluCont, Jump,
					Inst[31:26], Inst[5:0], Zero);

	DataPath D0(Zero, PCout, ROUT, AluOut, WDATA, DataToReg, Branch, 
				AluMux, RegAddress, RegWrite, AluCont, Jump, Inst, RDATA, clk, reset);


endmodule



module Controller(DataToReg, DataWrite, Branch, AluMux, 
					RegAddress, RegWrite, AluCont, Jump,
					OpCode, Function, Zero);

	output DataToReg, DataWrite, Branch, AluMux, RegAddress, RegWrite, Jump;
	output [2:0] AluCont;
	input [5:0] OpCode, Function;
	input Zero;

	wire [1:0] AluOp;
	OpDecoder D0(DataToReg, DataWrite, Branch, AluMux, 
						RegAddress, RegWrite, Jump, AluOp, OpCode, Zero);
	FuncDecoder D1(AluCont, Function, AluOp);

endmodule


module OpDecoder(DataToReg, DataWrite, Branch, 
				AluMux, RegAddress, RegWrite, Jump, AluOp, OpCode, Zero);

		output  DataToReg, DataWrite, AluMux, RegAddress, RegWrite, Jump, Branch;
		output [1:0] AluOp;
		input [5:0] OpCode;
		input Zero;
		wire  Branch0;

		reg [8:0] controlsig;
		assign {RegWrite, RegAddress, AluMux, Branch0, DataWrite, DataToReg, Jump, AluOp} = controlsig;
		always @* begin
			case (OpCode)
				6'b0: controlsig = 9'b110000010; //R-type inst
				6'b100011: controlsig = 9'b101001000; //LW
				6'b101011: controlsig = 9'b001010000; //SW
				6'b001000: controlsig = 9'b000100001; //Beq
				6'b010000: controlsig = 9'b101000000; //Addi
				6'b000010: controlsig = 9'b000000100; //Jump
				default: controlsig = 9'bxxxxxxxxx;
			endcase
		end

		assign Branch = (Branch0 & Zero);
endmodule 

module FuncDecoder(AluCont, Function, AluOp);
	output reg[2:0] AluCont;
	input [5:0] Function;
	input [1:0] AluOp;

	always @* begin 
		case(AluOp)
			2'b0: AluCont = 3'b010; //Add;
			2'b01: AluCont = 3'b110; //Sub;
			2'b10: begin 
					case(Function) 
			 			 6'b100000: AluCont = 3'b010;//Add
			 			 6'b100010: AluCont = 3'b110;//Sub
			 			 6'b100100: AluCont = 3'b000; //And
			 			 6'b100101: AluCont = 3'b001;//Or
			 			 6'b101010: AluCont = 3'b111;//SLT
			 			 default: AluCont = 3'bxxx;
					endcase
					end
			default: AluCont = 3'bxxx;
		endcase
	end

endmodule 


module DataPath(Zero, PCout, ROUT, AluOut, WDATA, DataToReg, Branch, 
				AluMux, RegAddress, RegWrite, AluCont, Jump, Inst, RDATA, clk, reset);

	output Zero;
	output [15:0] PCout, ROUT;//ROUT used only for debugging 
	output [15:0] AluOut, WDATA;
	input DataToReg, Branch, AluMux, RegAddress, RegWrite, Jump, clk, reset;
	input[2:0] AluCont;
	input[15:0] RDATA; //Data from Data memory;
	input[31:0] Inst; //Instruction From Instruction memory;
	wire[15:0] W1,W2,WD3,D1,D2,RD1,RD2;
	wire[3:0] A1,A2,A3;

	assign WDATA = RD2;
	assign A1 = Inst[24:21];
	assign A2 = Inst[19:16];
	Mux M0(A3, Inst[19:16], Inst[14:11], RegAddress);
	Mux #16 M1 (WD3, AluOut, RDATA, DataToReg); //mux before RegFile
 	Mux #16 M2(W1, PCout+16'b1, PCout+Inst[15:0]+16'b1, Branch); //mux before counter
 	Mux #16 M3(W2, W1, Inst[15:0], Jump);
 	Mux #16 M4(D2, RD2, Inst[15:0], AluMux); //mux before ALU

	RegFile regf(RD1, RD2, ROUT, A1, A2, A3, WD3, RegWrite, clk);
	ALU Alu(AluOut, Zero, RD1, D2, AluCont);
	ProgramCounter PC(PCout, W2, clk, reset);

endmodule 

module Mux(Q, D0,D1, s);
	parameter bits = 4;
	output [bits-1:0] Q;
	input [bits-1:0] D0,D1;
	input s;

	assign Q = (s==0) ? D0 : D1;
endmodule 

module ALU(AluOut, Zero, RD1, RD2, AluCont);
	output Zero;
	output reg[15:0] AluOut;
	input [15:0] RD1, RD2;
	input [2:0] AluCont;

	assign Zero = (RD1==RD2);
	always @* begin 
		case (AluCont)
			3'b010: AluOut = RD1+RD2; 
			3'b110: AluOut = RD1-RD2;
			3'b000: AluOut = RD1&RD2;
			3'b001: AluOut = RD1|RD2;
			3'b111: if (RD1 < RD2) AluOut = 16'b1111_1111_1111_1111; else AluOut = 16'b0;
			default: AluOut = 16'bxxxx_xxxx_xxxx_xxxx;
		endcase
	end

endmodule 


module ProgramCounter(PCout, D, clk, reset);
	output reg [15:0] PCout;
	input [15:0] D;
	input clk, reset;	

	always @(posedge clk, posedge reset)
		if (reset) PCout <= 0;
		else PCout <= D;

endmodule

module RegFile(RD1, RD2, ROUT, A1, A2, A3, WD3, WE,clk);
	output [15:0] RD1,RD2,ROUT;
	input [3:0] A1,A2,A3;
	input [15:0] WD3;
	input WE, clk;

	reg [16:0] rf[16:0];

	assign ROUT = rf[15];
	assign RD1 = (A1!=0) ? rf[A1] : 0;
	assign RD2 = (A2!=0) ? rf[A2] : 0;
	//register 0 is used for holding 0, however it is up to user
	//It is usefull to use one of 16 registers to hold zero temporary.

	always @(posedge clk)
		if (WE) rf[A3] <= WD3;

endmodule

module InnstructionMem(Inst, Address);
	output reg [31:0] Inst;
	input [15:0] Address;

	reg[31:0] ROM[10:0];
	
	initial
		$readmemh("instruction.txt", ROM); //gcd(32,28) program

	always @*
		Inst = ROM[Address];

endmodule


module DataMem(RDATA, Address, WDATA, WE, clk);
	output reg[15:0] RDATA;
	input [15:0] Address, WDATA;
	input WE, clk;

	reg [15:0] RAM[15:0];
	always @(posedge clk)
		if (WE) RAM[Address]<=WDATA;

	always @*
		if (!WE) RDATA = RAM[Address]; 

endmodule







module test;
	reg clk, reset;

	wire [15:0] ROUT;
	CPU MAIN(ROUT, clk,reset);

	initial #800 $finish;

	initial begin clk=0; forever #5 clk=~clk; end

	initial fork
		reset = 1;
		#10 reset =0;
	join


	initial begin
		$dumpfile("MIPS.vcd");
		$dumpvars(0,test);
	end

endmodule

16bitSingleCycleMIPS/MIPS.vcd
$date
	Wed Oct 10 16:10:03 2018
$end
$version
	Icarus Verilog
$end
$timescale
	100ps
$end
$scope module test $end
$var wire 16 ! ROUT [15:0] $end
$var reg 1 " clk $end
$var reg 1 # reset $end
$scope module MAIN $end
$var wire 16 $ AluOut [15:0] $end
$var wire 1 % DataWrite $end
$var wire 32 & Inst [31:0] $end
$var wire 16 ' PCout [15:0] $end
$var wire 16 ( RDATA [15:0] $end
$var wire 16 ) ROUT [15:0] $end
$var wire 16 * WDATA [15:0] $end
$var wire 1 + clk $end
$var wire 1 , reset $end
$scope module M $end
$var wire 3 - AluCont [2:0] $end
$var wire 1 . AluMux $end
$var wire 16 / AluOut [15:0] $end
$var wire 1 0 Branch $end
$var wire 1 1 DataToReg $end
$var wire 1 % DataWrite $end
$var wire 32 2 Inst [31:0] $end
$var wire 1 3 Jump $end
$var wire 16 4 PCout [15:0] $end
$var wire 16 5 RDATA [15:0] $end
$var wire 16 6 ROUT [15:0] $end
$var wire 1 7 RegAddress $end
$var wire 1 8 RegWrite $end
$var wire 16 9 WDATA [15:0] $end
$var wire 1 : Zero $end
$var wire 1 + clk $end
$var wire 1 , reset $end
$scope module C0 $end
$var wire 3 ; AluCont [2:0] $end
$var wire 1 . AluMux $end
$var wire 2 < AluOp [1:0] $end
$var wire 1 0 Branch $end
$var wire 1 1 DataToReg $end
$var wire 1 % DataWrite $end
$var wire 6 = Function [5:0] $end
$var wire 1 3 Jump $end
$var wire 6 > OpCode [5:0] $end
$var wire 1 7 RegAddress $end
$var wire 1 8 RegWrite $end
$var wire 1 : Zero $end
$scope module D0 $end
$var wire 1 . AluMux $end
$var wire 2 ? AluOp [1:0] $end
$var wire 1 0 Branch $end
$var wire 1 @ Branch0 $end
$var wire 1 1 DataToReg $end
$var wire 1 % DataWrite $end
$var wire 1 3 Jump $end
$var wire 6 A OpCode [5:0] $end
$var wire 1 7 RegAddress $end
$var wire 1 8 RegWrite $end
$var wire 1 : Zero $end
$var reg 9 B controlsig [8:0] $end
$upscope $end
$scope module D1 $end
$var wire 2 C AluOp [1:0] $end
$var wire 6 D Function [5:0] $end
$var reg 3 E AluCont [2:0] $end
$upscope $end
$upscope $end
$scope module D0 $end
$var wire 4 F A1 [3:0] $end
$var wire 4 G A2 [3:0] $end
$var wire 4 H A3 [3:0] $end
$var wire 3 I AluCont [2:0] $end
$var wire 1 . AluMux $end
$var wire 16 J AluOut [15:0] $end
$var wire 1 0 Branch $end
$var wire 16 K D2 [15:0] $end
$var wire 1 1 DataToReg $end
$var wire 32 L Inst [31:0] $end
$var wire 1 3 Jump $end
$var wire 16 M PCout [15:0] $end
$var wire 16 N RD1 [15:0] $end
$var wire 16 O RD2 [15:0] $end
$var wire 16 P RDATA [15:0] $end
$var wire 16 Q ROUT [15:0] $end
$var wire 1 7 RegAddress $end
$var wire 1 8 RegWrite $end
$var wire 16 R W1 [15:0] $end
$var wire 16 S W2 [15:0] $end
$var wire 16 T WD3 [15:0] $end
$var wire 16 U WDATA [15:0] $end
$var wire 1 : Zero $end
$var wire 1 + clk $end
$var wire 1 , reset $end
$scope module M0 $end
$var wire 4 V D0 [3:0] $end
$var wire 4 W D1 [3:0] $end
$var wire 4 X Q [3:0] $end
$var wire 1 7 s $end
$upscope $end
$scope module M1 $end
$var wire 16 Y D0 [15:0] $end
$var wire 16 Z D1 [15:0] $end
$var wire 16 [ Q [15:0] $end
$var wire 1 1 s $end
$upscope $end
$scope module M2 $end
$var wire 16 \ D0 [15:0] $end
$var wire 16 ] D1 [15:0] $end
$var wire 16 ^ Q [15:0] $end
$var wire 1 0 s $end
$upscope $end
$scope module M3 $end
$var wire 16 _ D0 [15:0] $end
$var wire 16 ` D1 [15:0] $end
$var wire 16 a Q [15:0] $end
$var wire 1 3 s $end
$upscope $end
$scope module M4 $end
$var wire 16 b D0 [15:0] $end
$var wire 16 c D1 [15:0] $end
$var wire 16 d Q [15:0] $end
$var wire 1 . s $end
$upscope $end
$scope module regf $end
$var wire 4 e A1 [3:0] $end
$var wire 4 f A2 [3:0] $end
$var wire 4 g A3 [3:0] $end
$var wire 16 h RD1 [15:0] $end
$var wire 16 i RD2 [15:0] $end
$var wire 16 j ROUT [15:0] $end
$var wire 16 k WD3 [15:0] $end
$var wire 1 8 WE $end
$var wire 1 + clk $end
$upscope $end
$scope module Alu $end
$var wire 3 l AluCont [2:0] $end
$var wire 16 m RD1 [15:0] $end
$var wire 16 n RD2 [15:0] $end
$var wire 1 : Zero $end
$var reg 16 o AluOut [15:0] $end
$upscope $end
$scope module PC $end
$var wire 16 p D [15:0] $end
$var wire 1 + clk $end
$var wire 1 , reset $end
$var reg 16 q PCout [15:0] $end
$upscope $end
$upscope $end
$upscope $end
$scope module I $end
$var wire 16 r Address [15:0] $end
$var reg 32 s Inst [31:0] $end
$upscope $end
$scope module D $end
$var wire 16 t Address [15:0] $end
$var wire 16 u WDATA [15:0] $end
$var wire 1 % WE $end
$var wire 1 + clk $end
$var reg 16 v RDATA [15:0] $end
$upscope $end
$upscope $end
$upscope $end
$enddefinitions $end
#0
$dumpvars
bx v
bx u
b100000 t
b1000000000000010000000000100000 s
b0 r
b0 q
b1 p
b100000 o
b100000 n
b0 m
b10 l
b100000 k
bz j
bx i
b0 h
b1 g
b1 f
b0 e
b100000 d
b100000 c
bx b
b1 a
b100000 `
b1 _
b1 ^
b100001 ]
b1 \
b100000 [
bx Z
b100000 Y
b1 X
b0 W
b1 V
bx U
b100000 T
b1 S
b1 R
bz Q
bx P
bx O
b0 N
b0 M
b1000000000000010000000000100000 L
b100000 K
b100000 J
b10 I
b1 H
b1 G
b0 F
b10 E
b100000 D
b0 C
b101000000 B
b10000 A
0@
b0 ?
b10000 >
b100000 =
b0 <
b10 ;
0:
bx 9
18
07
bz 6
bx 5
b0 4
03
b1000000000000010000000000100000 2
01
00
b100000 /
1.
b10 -
1,
0+
bx *
bz )
bx (
b0 '
b1000000000000010000000000100000 &
0%
b100000 $
1#
0"
bz !
$end
#50
b100000 O
b100000 b
b100000 i
b100000 *
b100000 9
b100000 U
b100000 u
1"
1+
#100
0"
0+
0#
0,
#150
b11100 T
b11100 [
b11100 k
b11100 o
b11100 $
b11100 /
b11100 J
b11100 Y
b11100 t
bx O
bx b
bx i
bx *
bx 9
bx U
bx u
b11100 K
b11100 d
b11100 n
b10 H
b10 X
b10 g
b10 S
b10 a
b10 p
b11100 c
b11100 `
b10 V
b10 G
b10 f
b11100 =
b11100 D
b10 R
b10 ^
b10 _
b1000000000000100000000000011100 s
b1000000000000100000000000011100 &
b1000000000000100000000000011100 2
b1000000000000100000000000011100 L
b1 q
b11110 ]
b10 \
b1 '
b1 4
b1 M
b1 r
1"
1+
#200
0"
0+
#250
b100 T
b100 [
b100 k
b110 E
b110 -
b110 ;
b110 I
b110 l
b100 o
b100 $
b100 /
b100 J
b100 Y
b100 t
b100000 N
b100000 h
b100000 m
08
0.
1@
b1 <
b1 ?
b1 C
b11100 K
b11100 d
b11100 n
b100001 B
b11100 O
b11100 b
b11100 i
b11100 *
b11100 9
b11100 U
b11100 u
b11 S
b11 a
b11 p
b110 c
b110 `
b1 F
b1 e
b110 =
b110 D
b1000 >
b1000 A
b11 R
b11 ^
b11 _
b100000001000100000000000000110 s
b100000001000100000000000000110 &
b100000001000100000000000000110 2
b100000001000100000000000000110 L
b10 q
b1001 ]
b11 \
b10 '
b10 4
b10 M
b10 r
1"
1+
#300
0"
0+
#350
b0 T
b0 [
b0 k
b0 o
b0 $
b0 /
b0 J
b0 Y
b0 t
b11 H
b11 X
b11 g
b111 E
b111 -
b111 ;
b111 I
b111 l
18
17
0@
b10 <
b10 ?
b10 C
b110000010 B
b100 S
b100 a
b100 p
b1100000101010 c
b1100000101010 `
b11 W
b101010 =
b101010 D
b0 >
b0 A
b100 R
b100 ^
b100 _
b1000100001100000101010 s
b1000100001100000101010 &
b1000100001100000101010 2
b1000100001100000101010 L
b11 q
b1100000101110 ]
b100 \
b11 '
b11 4
b11 M
b11 r
1"
1+
#400
0"
0+
#450
10
1:
b0 K
b0 d
b0 n
b0 T
b0 [
b0 k
b0 O
b0 b
b0 i
b0 *
b0 9
b0 U
b0 u
b0 N
b0 h
b0 m
b0 o
b0 $
b0 /
b0 J
b0 Y
b0 t
08
07
1@
b1 <
b1 ?
b1 C
b0 H
b0 X
b0 g
b110 E
b110 -
b110 ;
b110 I
b110 l
b100001 B
b111 S
b111 a
b111 p
b10 c
b10 `
b0 W
b0 V
b0 G
b0 f
b11 F
b11 e
b10 =
b10 D
b1000 >
b1000 A
b111 R
b111 ^
b111 _
b100000011000000000000000000010 s
b100000011000000000000000000010 &
b100000011000000000000000000010 2
b100000011000000000000000000010 L
b100 q
b111 ]
b101 \
b100 '
b100 4
b100 M
b100 r
1"
1+
#500
0"
0+
#550
b100 T
b100 [
b100 k
b11100 K
b11100 d
b11100 n
b100 o
b100 $
b100 /
b100 J
b100 Y
b100 t
00
b11100 O
b11100 b
b11100 i
b11100 *
b11100 9
b11100 U
b11100 u
0:
b100000 N
b100000 h
b100000 m
18
17
0@
b10 <
b10 ?
b10 C
b1 H
b1 X
b1 g
b110000010 B
b1000 S
b1000 a
b1000 p
b100000100010 c
b100000100010 `
b1 W
b10 V
b10 G
b10 f
b1 F
b1 e
b100010 =
b100010 D
b0 >
b0 A
b1000 R
b1000 ^
b1000 _
b1000100000100000100010 s
b1000100000100000100010 &
b1000100000100000100010 2
b1000100000100000100010 L
b111 q
b100000101010 ]
b1000 \
b111 '
b111 4
b111 M
b111 r
1"
1+
#600
0"
0+
#650
1:
b0 K
b0 d
b0 n
b0 T
b0 [
b0 k
b0 O
b0 b
b0 i
b0 *
b0 9
b0 U
b0 u
08
07
13
b0 <
b0 ?
b0 C
b0 o
b0 $
b0 /
b0 J
b0 Y
b0 t
b0 H
b0 X
b0 g
b10 E
b10 -
b10 ;
b10 I
b10 l
b100 B
b0 N
b0 h
b0 m
b10 S
b10 a
b10 p
b10 c
b10 `
b0 W
b0 V
b0 G
b0 f
b0 F
b0 e
b10 =
b10 D
b10 >
b10 A
b1001 R
b1001 ^
b1001 _
b1000000000000000000000000010 s
b1000000000000000000000000010 &
b1000000000000000000000000010 2
b1000000000000000000000000010 L
b1000 q
b1011 ]
b1001 \
b1000 '
b1000 4
b1000 M
b1000 r
1"
1+
#700
0"
0+
#750
b1111111111101000 T
b1111111111101000 [
b1111111111101000 k
b11100 K
b11100 d
b11100 n
b1111111111101000 o
b1111111111101000 $
b1111111111101000 /
b1111111111101000 J
b1111111111101000 Y
b1111111111101000 t
b110 E
b110 -
b110 ;
b110 I
b110 l
b11100 O
b11100 b
b11100 i
b11100 *
b11100 9
b11100 U
b11100 u
0:
b100 N
b100 h
b100 m
1@
03
b1 <
b1 ?
b1 C
b11 S
b11 a
b11 p
b10 H
b10 X
b10 g
b100001 B
b110 c
b110 `
b10 V
b10 G
b10 f
b1 F
b1 e
b110 =
b110 D
b1000 >
b1000 A
b11 R
b11 ^
b11 _
b100000001000100000000000000110 s
b100000001000100000000000000110 &
b100000001000100000000000000110 2
b100000001000100000000000000110 L
b10 q
b1001 ]
b11 \
b10 '
b10 4
b10 M
b10 r
1"
1+
#800
0"
0+
#850
b1111111111111111 T
b1111111111111111 [
b1111111111111111 k
b1111111111111111 o
b1111111111111111 $
b1111111111111111 /
b1111111111111111 J
b1111111111111111 Y
b1111111111111111 t
b11 H
b11 X
b11 g
b111 E
b111 -
b111 ;
b111 I
b111 l
18
17
0@
b10 <
b10 ?
b10 C
b110000010 B
b100 S
b100 a
b100 p
b1100000101010 c
b1100000101010 `
b11 W
b101010 =
b101010 D
b0 >
b0 A
b100 R
b100 ^
b100 _
b1000100001100000101010 s
b1000100001100000101010 &
b1000100001100000101010 2
b1000100001100000101010 L
b11 q
b1100000101110 ]
b100 \
b11 '
b11 4
b11 M
b11 r
1"
1+
#900
0"
0+
#950
b0 K
b0 d
b0 n
b1111111111111111 T
b1111111111111111 [
b1111111111111111 k
b0 O
b0 b
b0 i
b0 *
b0 9
b0 U
b0 u
b1111111111111111 N
b1111111111111111 h
b1111111111111111 m
b1111111111111111 o
b1111111111111111 $
b1111111111111111 /
b1111111111111111 J
b1111111111111111 Y
b1111111111111111 t
08
07
1@
b1 <
b1 ?
b1 C
b0 H
b0 X
b0 g
b110 E
b110 -
b110 ;
b110 I
b110 l
b100001 B
b101 S
b101 a
b101 p
b10 c
b10 `
b0 W
b0 V
b0 G
b0 f
b11 F
b11 e
b10 =
b10 D
b1000 >
b1000 A
b101 R
b101 ^
b101 _
b100000011000000000000000000010 s
b100000011000000000000000000010 &
b100000011000000000000000000010 2
b100000011000000000000000000010 L
b100 q
b111 ]
b101 \
b100 '
b100 4
b100 M
b100 r
1"
1+
#1000
0"
0+
#1050
b11000 T
b11000 [
b11000 k
b100 K
b100 d
b100 n
b11000 o
b11000 $
b11000 /
b11000 J
b11000 Y
b11000 t
b100 O
b100 b
b100 i
b100 *
b100 9
b100 U
b100 u
b11100 N
b11100 h
b11100 m
18
17
0@
b10 <
b10 ?
b10 C
b10 H
b10 X
b10 g
b110000010 B
b110 S
b110 a
b110 p
b1000000100010 c
b1000000100010 `
b10 W
b1 V
b1 G
b1 f
b10 F
b10 e
b100010 =
b100010 D
b0 >
b0 A
b110 R
b110 ^
b110 _
b10000010001000000100010 s
b10000010001000000100010 &
b10000010001000000100010 2
b10000010001000000100010 L
b101 q
b1000000101000 ]
b110 \
b101 '
b101 4
b101 M
b101 r
1"
1+
#1100
0"
0+
#1150
1:
b0 K
b0 d
b0 n
b0 T
b0 [
b0 k
b0 O
b0 b
b0 i
b0 *
b0 9
b0 U
b0 u
08
07
13
b0 <
b0 ?
b0 C
b0 o
b0 $
b0 /
b0 J
b0 Y
b0 t
b0 H
b0 X
b0 g
b10 E
b10 -
b10 ;
b10 I
b10 l
b100 B
b0 N
b0 h
b0 m
b10 S
b10 a
b10 p
b10 c
b10 `
b0 W
b0 V
b0 G
b0 f
b0 F
b0 e
b10 =
b10 D
b10 >
b10 A
b111 R
b111 ^
b111 _
b1000000000000000000000000010 s
b1000000000000000000000000010 &
b1000000000000000000000000010 2
b1000000000000000000000000010 L
b110 q
b1001 ]
b111 \
b110 '
b110 4
b110 M
b110 r
1"
1+
#1200
0"
0+
#1250
b1111111111101100 T
b1111111111101100 [
b1111111111101100 k
b11000 K
b11000 d
b11000 n
b1111111111101100 o
b1111111111101100 $
b1111111111101100 /
b1111111111101100 J
b1111111111101100 Y
b1111111111101100 t
b110 E
b110 -
b110 ;
b110 I
b110 l
b11000 O
b11000 b
b11000 i
b11000 *
b11000 9
b11000 U
b11000 u
0:
b100 N
b100 h
b100 m
1@
03
b1 <
b1 ?
b1 C
b11 S
b11 a
b11 p
b10 H
b10 X
b10 g
b100001 B
b110 c
b110 `
b10 V
b10 G
b10 f
b1 F
b1 e
b110 =
b110 D
b1000 >
b1000 A
b11 R
b11 ^
b11 _
b100000001000100000000000000110 s
b100000001000100000000000000110 &
b100000001000100000000000000110 2
b100000001000100000000000000110 L
b10 q
b1001 ]
b11 \
b10 '
b10 4
b10 M
b10 r
1"
1+
#1300
0"
0+
#1350
b1111111111111111 T
b1111111111111111 [
b1111111111111111 k
b1111111111111111 o
b1111111111111111 $
b1111111111111111 /
b1111111111111111 J
b1111111111111111 Y
b1111111111111111 t
b11 H
b11 X
b11 g
b111 E
b111 -
b111 ;
b111 I
b111 l
18
17
0@
b10 <
b10 ?
b10 C
b110000010 B
b100 S
b100 a
b100 p
b1100000101010 c
b1100000101010 `
b11 W
b101010 =
b101010 D
b0 >
b0 A
b100 R
b100 ^
b100 _
b1000100001100000101010 s
b1000100001100000101010 &
b1000100001100000101010 2
b1000100001100000101010 L
b11 q
b1100000101110 ]
b100 \
b11 '
b11 4
b11 M
b11 r
1"
1+
#1400
0"
0+
#1450
b0 K
b0 d
b0 n
b1111111111111111 T
b1111111111111111 [
b1111111111111111 k
b0 O
b0 b
b0 i
b0 *
b0 9
b0 U
b0 u
b1111111111111111 N
b1111111111111111 h
b1111111111111111 m
b1111111111111111 o
b1111111111111111 $
b1111111111111111 /
b1111111111111111 J
b1111111111111111 Y
b1111111111111111 t
08
07
1@
b1 <
b1 ?
b1 C
b0 H
b0 X
b0 g
b110 E
b110 -
b110 ;
b110 I
b110 l
b100001 B
b101 S
b101 a
b101 p
b10 c
b10 `
b0 W
b0 V
b0 G
b0 f
b11 F
b11 e
b10 =
b10 D
b1000 >
b1000 A
b101 R
b101 ^
b101 _
b100000011000000000000000000010 s
b100000011000000000000000000010 &
b100000011000000000000000000010 2
b100000011000000000000000000010 L
b100 q
b111 ]
b101 \
b100 '
b100 4
b100 M
b100 r
1"
1+
#1500
0"
0+
#1550
b10100 T
b10100 [
b10100 k
b100 K
b100 d
b100 n
b10100 o
b10100 $
b10100 /
b10100 J
b10100 Y
b10100 t
b100 O
b100 b
b100 i
b100 *
b100 9
b100 U
b100 u
b11000 N
b11000 h
b11000 m
18
17
0@
b10 <
b10 ?
b10 C
b10 H
b10 X
b10 g
b110000010 B
b110 S
b110 a
b110 p
b1000000100010 c
b1000000100010 `
b10 W
b1 V
b1 G
b1 f
b10 F
b10 e
b100010 =
b100010 D
b0 >
b0 A
b110 R
b110 ^
b110 _
b10000010001000000100010 s
b10000010001000000100010 &
b10000010001000000100010 2
b10000010001000000100010 L
b101 q
b1000000101000 ]
b110 \
b101 '
b101 4
b101 M
b101 r
1"
1+
#1600
0"
0+
#1650
1:
b0 K
b0 d
b0 n
b0 T
b0 [
b0 k
b0 O
b0 b
b0 i
b0 *
b0 9
b0 U
b0 u
08
07
13
b0 <
b0 ?
b0 C
b0 o
b0 $
b0 /
b0 J
b0 Y
b0 t
b0 H
b0 X
b0 g
b10 E
b10 -
b10 ;
b10 I
b10 l
b100 B
b0 N
b0 h
b0 m
b10 S
b10 a
b10 p
b10 c
b10 `
b0 W
b0 V
b0 G
b0 f
b0 F
b0 e
b10 =
b10 D
b10 >
b10 A
b111 R
b111 ^
b111 _
b1000000000000000000000000010 s
b1000000000000000000000000010 &
b1000000000000000000000000010 2
b1000000000000000000000000010 L
b110 q
b1001 ]
b111 \
b110 '
b110 4
b110 M
b110 r
1"
1+
#1700
0"
0+
#1750
b1111111111110000 T
b1111111111110000 [
b1111111111110000 k
b10100 K
b10100 d
b10100 n
b1111111111110000 o
b1111111111110000 $
b1111111111110000 /
b1111111111110000 J
b1111111111110000 Y
b1111111111110000 t
b110 E
b110 -
b110 ;
b110 I
b110 l
b10100 O
b10100 b
b10100 i
b10100 *
b10100 9
b10100 U
b10100 u
0:
b100 N
b100 h
b100 m
1@
03
b1 <
b1 ?
b1 C
b11 S
b11 a
b11 p
b10 H
b10 X
b10 g
b100001 B
b110 c
b110 `
b10 V
b10 G
b10 f
b1 F
b1 e
b110 =
b110 D
b1000 >
b1000 A
b11 R
b11 ^
b11 _
b100000001000100000000000000110 s
b100000001000100000000000000110 &
b100000001000100000000000000110 2
b100000001000100000000000000110 L
b10 q
b1001 ]
b11 \
b10 '
b10 4
b10 M
b10 r
1"
1+
#1800
0"
0+
#1850
b1111111111111111 T
b1111111111111111 [
b1111111111111111 k
b1111111111111111 o
b1111111111111111 $
b1111111111111111 /
b1111111111111111 J
b1111111111111111 Y
b1111111111111111 t
b11 H
b11 X
b11 g
b111 E
b111 -
b111 ;
b111 I
b111 l
18
17
0@
b10 <
b10 ?
b10 C
b110000010 B
b100 S
b100 a
b100 p
b1100000101010 c
b1100000101010 `
b11 W
b101010 =
b101010 D
b0 >
b0 A
b100 R
b100 ^
b100 _
b1000100001100000101010 s
b1000100001100000101010 &
b1000100001100000101010 2
b1000100001100000101010 L
b11 q
b1100000101110 ]
b100 \
b11 '
b11 4
b11 M
b11 r
1"
1+
#1900
0"
0+
#1950
b0 K
b0 d
b0 n
b1111111111111111 T
b1111111111111111 [
b1111111111111111 k
b0 O
b0 b
b0 i
b0 *
b0 9
b0 U
b0 u
b1111111111111111 N
b1111111111111111 h
b1111111111111111 m
b1111111111111111 o
b1111111111111111 $
b1111111111111111 /
b1111111111111111 J
b1111111111111111 Y
b1111111111111111 t
08
07
1@
b1 <
b1 ?
b1 C
b0 H
b0 X
b0 g
b110 E
b110 -
b110 ;
b110 I
b110 l
b100001 B
b101 S
b101 a
b101 p
b10 c
b10 `
b0 W
b0 V
b0 G
b0 f
b11 F
b11 e
b10 =
b10 D
b1000 >
b1000 A
b101 R
b101 ^
b101 _
b100000011000000000000000000010 s
b100000011000000000000000000010 &
b100000011000000000000000000010 2
b100000011000000000000000000010 L
b100 q
b111 ]
b101 \
b100 '
b100 4
b100 M
b100 r
1"
1+
#2000
0"
0+
#2050
b10000 T
b10000 [
b10000 k
b100 K
b100 d
b100 n
b10000 o
b10000 $
b10000 /
b10000 J
b10000 Y
b10000 t
b100 O
b100 b
b100 i
b100 *
b100 9
b100 U
b100 u
b10100 N
b10100 h
b10100 m
18
17
0@
b10 <
b10 ?
b10 C
b10 H
b10 X
b10 g
b110000010 B
b110 S
b110 a
b110 p
b1000000100010 c
b1000000100010 `
b10 W
b1 V
b1 G
b1 f
b10 F
b10 e
b100010 =
b100010 D
b0 >
b0 A
b110 R
b110 ^
b110 _
b10000010001000000100010 s
b10000010001000000100010 &
b10000010001000000100010 2
b10000010001000000100010 L
b101 q
b1000000101000 ]
b110 \
b101 '
b101 4
b101 M
b101 r
1"
1+
#2100
0"
0+
#2150
1:
b0 K
b0 d
b0 n
b0 T
b0 [
b0 k
b0 O
b0 b
b0 i
b0 *
b0 9
b0 U
b0 u
08
07
13
b0 <
b0 ?
b0 C
b0 o
b0 $
b0 /
b0 J
b0 Y
b0 t
b0 H
b0 X
b0 g
b10 E
b10 -
b10 ;
b10 I
b10 l
b100 B
b0 N
b0 h
b0 m
b10 S
b10 a
b10 p
b10 c
b10 `
b0 W
b0 V
b0 G
b0 f
b0 F
b0 e
b10 =
b10 D
b10 >
b10 A
b111 R
b111 ^
b111 _
b1000000000000000000000000010 s
b1000000000000000000000000010 &
b1000000000000000000000000010 2
b1000000000000000000000000010 L
b110 q
b1001 ]
b111 \
b110 '
b110 4
b110 M
b110 r
1"
1+
#2200
0"
0+
#2250
b1111111111110100 T
b1111111111110100 [
b1111111111110100 k
b10000 K
b10000 d
b10000 n
b1111111111110100 o
b1111111111110100 $
b1111111111110100 /
b1111111111110100 J
b1111111111110100 Y
b1111111111110100 t
b110 E
b110 -
b110 ;
b110 I
b110 l
b10000 O
b10000 b
b10000 i
b10000 *
b10000 9
b10000 U
b10000 u
0:
b100 N
b100 h
b100 m
1@
03
b1 <
b1 ?
b1 C
b11 S
b11 a
b11 p
b10 H
b10 X
b10 g
b100001 B
b110 c
b110 `
b10 V
b10 G
b10 f
b1 F
b1 e
b110 =
b110 D
b1000 >
b1000 A
b11 R
b11 ^
b11 _
b100000001000100000000000000110 s
b100000001000100000000000000110 &
b100000001000100000000000000110 2
b100000001000100000000000000110 L
b10 q
b1001 ]
b11 \
b10 '
b10 4
b10 M
b10 r
1"
1+
